{
    "fluentMethods": true,
    "relationships": [],
    "fields": [
        {
            "fieldName": "id_fuente",
            "fieldType": "String",
            "fieldValidateRules": [
                "required"
            ]
        },
        {
            "fieldName": "cantidad_apuestas",
            "fieldType": "Integer",
            "fieldValidateRules": [
                "required"
            ]
        },
        {
            "fieldName": "valor_total",
            "fieldType": "BigDecimal",
            "fieldValidateRules": [
                "required",
                "max"
            ],
            "fieldValidateRulesMax": "100000000"
        },
        {
            "fieldName": "fecha",
            "fieldType": "ZonedDateTime",
            "fieldValidateRules": [
                "required"
            ]
        },
        {
            "fieldName": "participa_misterioso",
            "fieldType": "String",
            "fieldValidateRules": [
                "required"
            ]
        }
    ],
    "changelogDate": "20171023201710",
    "dto": "mapstruct",
    "service": "serviceImpl",
    "entityTableName": "ticket",
    "jpaMetamodelFiltering": false,
    "pagination": "pagination"
}
